ButterflyNet-1.1.0.dist-info/DESCRIPTION.rst
ButterflyNet-1.1.0.dist-info/METADATA
ButterflyNet-1.1.0.dist-info/RECORD
ButterflyNet-1.1.0.dist-info/WHEEL
ButterflyNet-1.1.0.dist-info/metadata.json
ButterflyNet-1.1.0.dist-info/pbr.json
ButterflyNet-1.1.0.dist-info/top_level.txt
bfnet/BFHandler.py
bfnet/Butterfly.py
bfnet/Net.py
bfnet/__init__.py
bfnet/util.py
bfnet/packets/PacketButterfly.py
bfnet/packets/PacketHandler.py
bfnet/packets/PacketNet.py
bfnet/packets/Packets.py
bfnet/packets/__init__.py
