Metadata-Version: 2.0
Name: ButterflyNet
Version: 1.1.0
Summary: A better networking library.
Home-page: https://butterflynet.veriny.tf
Author: Isaac Dickinson
Author-email: eyesismine@gmail.com
License: LGPLv3
Platform: UNKNOWN
Classifier: Development Status :: 4 - Beta
Classifier: License :: OSI Approved :: GNU Lesser General Public License v3 (LGPLv3)
Classifier: Programming Language :: Python :: 3 :: Only
Classifier: Programming Language :: Python :: 3.4
Classifier: Programming Language :: Python :: 3.5
Classifier: Topic :: Internet
Classifier: Topic :: Software Development :: Libraries
Requires-Dist: msgpack-python
